LICENSE
MANIFEST.in
README.rst
buildout.cfg
requirements.txt
setup.py
version.txt
bob/__init__.py
bob.db.atvskeystroke.egg-info/PKG-INFO
bob.db.atvskeystroke.egg-info/SOURCES.txt
bob.db.atvskeystroke.egg-info/dependency_links.txt
bob.db.atvskeystroke.egg-info/entry_points.txt
bob.db.atvskeystroke.egg-info/not-zip-safe
bob.db.atvskeystroke.egg-info/requires.txt
bob.db.atvskeystroke.egg-info/top_level.txt
bob/db/__init__.py
bob/db/atvskeystroke/__init__.py
bob/db/atvskeystroke/create.py
bob/db/atvskeystroke/driver.py
bob/db/atvskeystroke/models.py
bob/db/atvskeystroke/query.py
bob/db/atvskeystroke/test.py
doc/conf.py
doc/index.rst