Metadata-Version: 1.2
Name: bob.db.atvskeystroke
Version: 2.1.6
Summary: ATVS-Keystroke Database Access API for Bob
Home-page: https://gitlab.idiap.ch/bob/bob.db.atvskeystroke
Author: Marta Gomez-Barrero
Author-email: marta.gomez-barrero@h-da.de
Maintainer: Andre Anjos
Maintainer-email: andre.anjos@idiap.ch
License: BSD
Keywords: keystroke recognition,bob,bob.db,atvs
Platform: UNKNOWN
Classifier: Framework :: Bob
Classifier: Development Status :: 4 - Beta
Classifier: Environment :: Console
Classifier: Intended Audience :: Developers
Classifier: Intended Audience :: Education
Classifier: Intended Audience :: Science/Research
Classifier: License :: OSI Approved :: BSD License
Classifier: Natural Language :: English
Classifier: Programming Language :: Python
Classifier: Programming Language :: Python :: 3
Classifier: Topic :: Scientific/Engineering :: Artificial Intelligence
Classifier: Topic :: Database :: Front-Ends
